pycounts_lennonay/__init__.py
pycounts_lennonay/plotting.py
pycounts_lennonay/pycounts_lennonay.py
pycounts_lennonay-0.1.0.dist-info/LICENSE
pycounts_lennonay-0.1.0.dist-info/WHEEL
pycounts_lennonay-0.1.0.dist-info/METADATA
pycounts_lennonay-0.1.0.dist-info/RECORD
